zxcvbn-stubs/METADATA.toml
zxcvbn-stubs/__init__.pyi
zxcvbn-stubs/adjacency_graphs.pyi
zxcvbn-stubs/feedback.pyi
zxcvbn-stubs/frequency_lists.pyi
zxcvbn-stubs/matching.pyi
zxcvbn-stubs/scoring.pyi
zxcvbn-stubs/time_estimates.pyi
types_zxcvbn-4.4.1.6.dist-info/METADATA
types_zxcvbn-4.4.1.6.dist-info/WHEEL
types_zxcvbn-4.4.1.6.dist-info/top_level.txt
types_zxcvbn-4.4.1.6.dist-info/RECORD
